LICENSE.txt
MANIFEST.in
README.rst
pyproject.toml
setup.py
tutor_indigo.egg-info/PKG-INFO
tutor_indigo.egg-info/SOURCES.txt
tutor_indigo.egg-info/dependency_links.txt
tutor_indigo.egg-info/entry_points.txt
tutor_indigo.egg-info/requires.txt
tutor_indigo.egg-info/top_level.txt
tutorindigo/__about__.py
tutorindigo/__init__.py
tutorindigo/plugin.py
tutorindigo/patches/mfe-env-config-buildtime-definitions
tutorindigo/patches/mfe-env-config-buildtime-imports
tutorindigo/patches/mfe-env-config-runtime-definitions
tutorindigo/templates/indigo/cms/static/images/favicon.ico
tutorindigo/templates/indigo/cms/static/images/studio-logo.png
tutorindigo/templates/indigo/cms/static/sass/partials/cms/theme/_extras.scss
tutorindigo/templates/indigo/cms/static/sass/partials/cms/theme/_fonts.scss
tutorindigo/templates/indigo/cms/static/sass/partials/cms/theme/_variables-v1.scss
tutorindigo/templates/indigo/cms/static/sass/partials/cms/theme/_variables.scss
tutorindigo/templates/indigo/lms/static/fonts/CrimsonText-Bold.ttf
tutorindigo/templates/indigo/lms/static/fonts/CrimsonText-BoldItalic.ttf
tutorindigo/templates/indigo/lms/static/fonts/CrimsonText-Italic.ttf
tutorindigo/templates/indigo/lms/static/fonts/CrimsonText-Regular.ttf
tutorindigo/templates/indigo/lms/static/fonts/CrimsonText-SemiBold.ttf
tutorindigo/templates/indigo/lms/static/fonts/CrimsonText-SemiBoldItalic.ttf
tutorindigo/templates/indigo/lms/static/fonts/IBMPlexSans-Bold.ttf
tutorindigo/templates/indigo/lms/static/fonts/IBMPlexSans-BoldItalic.ttf
tutorindigo/templates/indigo/lms/static/fonts/IBMPlexSans-ExtraLight.ttf
tutorindigo/templates/indigo/lms/static/fonts/IBMPlexSans-ExtraLightItalic.ttf
tutorindigo/templates/indigo/lms/static/fonts/IBMPlexSans-Italic.ttf
tutorindigo/templates/indigo/lms/static/fonts/IBMPlexSans-Light.ttf
tutorindigo/templates/indigo/lms/static/fonts/IBMPlexSans-LightItalic.ttf
tutorindigo/templates/indigo/lms/static/fonts/IBMPlexSans-Medium.ttf
tutorindigo/templates/indigo/lms/static/fonts/IBMPlexSans-MediumItalic.ttf
tutorindigo/templates/indigo/lms/static/fonts/IBMPlexSans-Regular.ttf
tutorindigo/templates/indigo/lms/static/fonts/IBMPlexSans-SemiBold.ttf
